zkill_searchf/__init__.py
zkill_searchf/search.py
zkill_searchf-0.0.1.dist-info/LICENSE
zkill_searchf-0.0.1.dist-info/METADATA
zkill_searchf-0.0.1.dist-info/WHEEL
zkill_searchf-0.0.1.dist-info/entry_points.txt
zkill_searchf-0.0.1.dist-info/top_level.txt
zkill_searchf-0.0.1.dist-info/RECORD
