Metadata-Version: 2.1
Name: zkill-searchf
Version: 0.0.1
Summary: Search for EVE Killmails on Zkillboard by ship and equipments
Home-page: https://github.com/sxsing/zkill-searchf
Author: Chang Liu
Author-email: lcqwop@gmail.com
License: UNKNOWN
Platform: UNKNOWN
Classifier: Programming Language :: Python :: 3
Classifier: License :: OSI Approved :: MIT License
Classifier: Operating System :: OS Independent
Requires-Python: >=3.7
Requires-Dist: aiohttp
Requires-Dist: PyYAML
